fdbuild/__init__.py
fdbuild/__main__.py
fdbuild/arguments.py
fdbuild/chainer.py
fdbuild/config.py
fdbuild/defaulttexts.py
fdbuild/exceptions.py
fdbuild/log.py
fdbuild/main.py
fdbuild/pluginfactory.py
fdbuild/project.py
fdbuild/settings.py
fdbuild/stage.py
fdbuild/step.py
fdbuild/structurizer.py
fdbuild/templater.py
fdbuild/utils.py
fdbuild/work_unit.py
fdbuild/plugins/__init__.py
fdbuild/plugins/templates.py
fdbuild/plugins/stages/__init__.py
fdbuild/plugins/stages/build.py
fdbuild/plugins/stages/configure.py
fdbuild/plugins/stages/install.py
fdbuild/plugins/stages/source.py
fdbuild/plugins/steps/__init__.py
fdbuild/plugins/steps/autoconf.py
fdbuild/plugins/steps/cmake.py
fdbuild/plugins/steps/git.py
fdbuild/plugins/steps/make.py
fdbuild/plugins/steps/meson.py
fdbuild/plugins/steps/ninja.py
fdbuild/plugins/structurizers/__init__.py
fdbuild/plugins/structurizers/kde.py
fdbuild/templates/cmake.yaml
fdbuild/templates/default-autoconf.yaml
fdbuild/templates/default-cmake.yaml
fdbuild/templates/default-meson.yaml
fdbuild/templates/gcc.yaml
fdbuild/templates/kwinft.yaml
fdbuild/templates/libx.yaml
fdbuild/templates/linux-desktop-meta.yaml
fdbuild/templates/linux-graphics-meta.yaml
fdbuild/templates/llvm.yaml
fdbuild/templates/media.yaml
fdbuild/templates/qt5.yaml
fdbuild/templates/qt6.yaml
fdbuild/templates/wayland.yaml
fdbuild/templates/weston.yaml
fdbuild/templates/wlroots.yaml
fdbuild/templates/xcb.yaml
fdbuild/templates/xorgproto.yaml
fdbuild/templates/xserver.yaml
fdbuild/templates/drm/template.yaml
fdbuild/templates/kwinft-plasma-meta/kwinft-adapt.py
fdbuild/templates/kwinft-plasma-meta/template.yaml
fdbuild/templates/mesa/copy-cross-file.py
fdbuild/templates/mesa/meson-cross-file
fdbuild/templates/mesa/template.yaml
fdbuild-0.3.0.dist-info/LICENSE
fdbuild-0.3.0.dist-info/METADATA
fdbuild-0.3.0.dist-info/WHEEL
fdbuild-0.3.0.dist-info/entry_points.txt
fdbuild-0.3.0.dist-info/top_level.txt
fdbuild-0.3.0.dist-info/RECORD
