Metadata-Version: 2.1
Name: fdbuild
Version: 0.3.0
Summary: CLI tool to fulfill tasks on single projects or vast project hierarchies
Author-email: Roman Gilg <subdiff@gmail.com>
Project-URL: Homepage, https://gitlab.com/kwinft/fdbuild
Project-URL: Issues, https://gitlab.com/kwinft/fdbuild/-/issues
Classifier: Programming Language :: Python :: 3
Classifier: Programming Language :: Python :: 3.8
Classifier: Programming Language :: Python :: 3.9
Classifier: Programming Language :: Python :: 3.10
Classifier: Programming Language :: Python :: 3.11
Classifier: Programming Language :: Python :: 3.12
Classifier: License :: OSI Approved :: GNU General Public License v3 (GPLv3)
Classifier: Operating System :: OS Independent
Classifier: Topic :: Software Development :: Build Tools
Requires-Python: >=3.8
License-File: LICENSE
Requires-Dist: PyYAML
